pyfygentlescrap/__init__.py
pyfygentlescrap/warnings.py
pyfygentlescrap/yahoo/__init__.py
pyfygentlescrap/yahoo/yahoo_calendar.py
pyfygentlescrap/yahoo/yahoo_historical.py
pyfygentlescrap/yahoo/yahoo_screener.py
pyfygentlescrap/yahoo/yahoo_shared.py
pyfygentlescrap/yahoo/yahoo_ticker.py
PyFyGentleScrap-0.4.14.dist-info/LICENSE
PyFyGentleScrap-0.4.14.dist-info/METADATA
PyFyGentleScrap-0.4.14.dist-info/WHEEL
PyFyGentleScrap-0.4.14.dist-info/top_level.txt
PyFyGentleScrap-0.4.14.dist-info/RECORD
