Metadata-Version: 2.1
Name: PyFyGentleScrap
Version: 0.4.14
Summary: Unofficial Yahoo finance scrapper
Home-page: https://gitlab.com/OlivierLuG/pyfygentlescrap
Author: OlivierLuG
Author-email: not_a_valid_email@gmail.com
License: MIT
Platform: UNKNOWN
Classifier: Programming Language :: Python :: 3
Classifier: License :: OSI Approved :: MIT License
Classifier: Operating System :: OS Independent
Requires-Python: >=3.6
Requires-Dist: pandas (>=1.0)
Requires-Dist: requests
